[
	{
		"name": "1",
		"title": {
			"en": "The Time",
			"ru": "Время"
		},
		"link": "RqAyZ-gH4LQ"
	},
	{
		"name": "2",
		"title": {
			"en": "My Star",
			"ru": "Моя Звезда"
		},
		"link": "RIcOcQ0WeRg"
	},
	{
		"name": "3",
		"title": {
			"en": "The Musician",
			"ru": "Музыкант"
		},
		"link": "x6e2UMEKF7Q"
	},
	{
		"name": "4",
		"title": {
			"en": "The City",
			"ru": "Город"
		},
		"link": "hljD7m1ID28"
	},
	{
		"name": "5",
		"title": {
			"en": "Performance on TV",
			"ru": "Выступление на TV"
		},
		"link": "Z0OcUGPzI7g"
	},
	{
		"name": "6",
		"title": {
			"en": "Omen",
			"ru": "Знамение"
		},
		"link": "iVb9kHj7Ku0"
	},
	{
		"name": "8",
		"title": {
			"en": "Extinct Volcanoes",
			"ru": "Потухшие Вулканы"
		},
		"link": "w47jg4leCe4"
	},
	{
		"name": "9",
		"title": {
			"en": "Mysterious Voices",
			"ru": "Таинственные Голоса"
		},
		"link": "VMnIt0LT858"
	},
	{
		"name": "10",
		"title": {
			"en": "Dolphins In The Ocean",
			"ru": "Дельфины в Океане"
		},
		"link": "KhERjkrTj_Q"
	},
	{
		"name": "11",
		"title": {
			"en": "Voice In The Wilderness",
			"ru": "Голос Пустыни"
		},
		"link": "ViynIGKo9B0"
	},
	{
		"name": "12",
		"title": {
			"en": "Sky At Sunset",
			"ru": "Небо На Закате"
		},
		"link": "vt8XEtREUko"
	}
]
